{"components":{"schemas":{"models.rest.WSCreateGame":{"properties":{}},"WSPing":{"$ref":"#/components/schemas/models.rest.WSPing","type":"object"},"WSCreateGame":{"$ref":"#/components/schemas/models.rest.WSCreateGame","type":"object"},"WSPongMessage":{"$ref":"#/components/schemas/models.rest.WSPongMessage","type":"object"},"models.rest.WSPing":{"properties":{}},"models.rest.WSPongMessage":{"properties":{"success":{"type":"boolean"}},"required":["success"]},"models.rest.WSBroadcastMessage":{"properties":{"message":{"type":"string"}},"required":["message"]},"WSMessage":{"properties":{"msgType":{"$ref":"#/components/schemas/WSMessageType"},"data":{"type":"object","oneOf":[{"$ref":"#/components/schemas/WSBroadcastMessage"},{"$ref":"#/components/schemas/WSCreateGame"},{"$ref":"#/components/schemas/WSJoinGame"},{"$ref":"#/components/schemas/WSInboxMessage"}]}}},"models.rest.WSInboxMessage":{"properties":{"message":{"type":"string"}},"required":["message"]},"WSJoinGame":{"$ref":"#/components/schemas/models.rest.WSJoinGame","type":"object"},"models.rest.WSJoinGame":{"properties":{"id":{"type":"string"}},"required":["id"]},"WSBroadcastMessage":{"$ref":"#/components/schemas/models.rest.WSBroadcastMessage","type":"object"},"WSMessageType":{"type":"string","enum":["CreateGame","JoinGame","BroadcastMessage","InboxMessage","PingMessage","PongMessage"]},"WSInboxMessage":{"$ref":"#/components/schemas/models.rest.WSInboxMessage","type":"object"},"models.rest.ServerStatus":{"properties":{"time":{"type":"integer","format":"int64"},"address":{"type":"string"}},"required":["time","address"]}}},"openapi":"3.0.0","paths":{"/api/status":{"get":{"operationId":"status","tags":["routes"],"summary":"Gets status of server","description":"Returns the time and ip address of the server","responses":{"200":{"description":"success","content":{"application/json":{"schema":{"$ref":"#/components/schemas/models.rest.ServerStatus"}}}}}}}},"info":{"description":"","title":"Security Trader API","version":"1.0-SNAPSHOT"},"tags":[{"name":"routes"}]}